recsys_metrics_polars/__init__.py
recsys_metrics_polars/avg_precision.py
recsys_metrics_polars/base.py
recsys_metrics_polars/constants.py
recsys_metrics_polars/data_info.py
recsys_metrics_polars/hit_at_k.py
recsys_metrics_polars/precision.py
recsys_metrics_polars/recall.py
recsys_metrics_polars/utils.py
recsys_metrics_polars-0.0.3.dist-info/LICENSE
recsys_metrics_polars-0.0.3.dist-info/METADATA
recsys_metrics_polars-0.0.3.dist-info/WHEEL
recsys_metrics_polars-0.0.3.dist-info/RECORD
