Metadata-Version: 2.1
Name: recsys-metrics-polars
Version: 0.0.3
Summary: A pyhon package for computing recomendations metrics based on polars dataframes
Home-page: https://github.com/KernelA/recsys-metrics-polars
License: MIT
Author: KernelA
Requires-Python: >=3.9,<4.0
Classifier: License :: OSI Approved :: MIT License
Classifier: Programming Language :: Python :: 3
Classifier: Programming Language :: Python :: 3.9
Classifier: Programming Language :: Python :: 3.10
Classifier: Programming Language :: Python :: 3.11
Classifier: Programming Language :: Python :: 3.12
Requires-Dist: polars (>=0.19,<0.20)
Project-URL: Bug Tracker, https://github.com/KernelA/recsys-metrics-polars/issues
Project-URL: Repository, https://github.com/KernelA/recsys-metrics-polars
